{
  "dataset": "X Rap X",
  "source_csv": "x_rap_x.csv",
  "metadata": {
    "track_count": 119,
    "unique_artists": 82,
    "date_range": {
      "start": "2025-01-28",
      "end": "2025-03-01"
    },
    "generated_at": "2025-10-06T21:11:20Z",
    "zero_fraction": {
      "valence": 0.0,
      "energy": 0.0,
      "danceability": 0.0,
      "acousticness": 0.0,
      "instrumentalness": 0.0,
      "liveness": 0.0
    }
  },
  "summary": {
    "audio_features": {
      "valence": {
        "mean": 0.47658712352970223,
        "std": 0.2990319939093818,
        "min": 0.005522117123602399,
        "max": 0.9868869366005173,
        "median": 0.4722149251619493,
        "count": 119,
        "zero_fraction": 0.0,
        "trend_7d": 0.5180188796426153
      },
      "energy": {
        "mean": 0.48514864494504895,
        "std": 0.286917809244892,
        "min": 0.005061583846218687,
        "max": 0.9856504541106007,
        "median": 0.5026790232288615,
        "count": 119,
        "zero_fraction": 0.0,
        "trend_7d": -0.5150262754841969
      },
      "danceability": {
        "mean": 0.503275934586909,
        "std": 0.2920994517355213,
        "min": 0.014393488629755868,
        "max": 0.9900538501042633,
        "median": 0.5222432600548044,
        "count": 119,
        "zero_fraction": 0.0,
        "trend_7d": -0.618960985365546
      },
      "acousticness": {
        "mean": 0.5191955459179551,
        "std": 0.31836044187904333,
        "min": 0.01083765148029836,
        "max": 0.9929647961193003,
        "median": 0.5456167893159349,
        "count": 119,
        "zero_fraction": 0.0,
        "trend_7d": 0.40718921484583703
      },
      "instrumentalness": {
        "mean": 0.5390182442865732,
        "std": 0.2950213830742959,
        "min": 0.014544665667881929,
        "max": 0.9997176732861306,
        "median": 0.5538542844013208,
        "count": 119,
        "zero_fraction": 0.0,
        "trend_7d": 0.822991845170613
      },
      "liveness": {
        "mean": 0.42959717676213816,
        "std": 0.2683092638627697,
        "min": 0.02007119777772637,
        "max": 0.9899602323899452,
        "median": 0.39785559904574164,
        "count": 119,
        "zero_fraction": 0.0,
        "trend_7d": -0.06212072611560382
      }
    },
    "sentiment": {},
    "emotion_profile": {},
    "recommendations": []
  }
}